README.md
setup.py
pycsk/__init__.py
pycsk/__main__.py
pycsk/csk.py
pycsk.egg-info/PKG-INFO
pycsk.egg-info/SOURCES.txt
pycsk.egg-info/dependency_links.txt
pycsk.egg-info/entry_points.txt
pycsk.egg-info/requires.txt
pycsk.egg-info/top_level.txt