Metadata-Version: 2.1
Name: pycsk
Version: 0.2.0
Summary: Clear sky charts in your terminal
Home-page: https://github.com/mohsaad/pydarksky
Author: Mohammad Saad
Author-email: mohammad.saad@outlook.com
License: MIT
Platform: UNKNOWN
Requires-Python: >=3.6
